rule34easy.py
rule34easy-0.1.2.dist-info/WHEEL
rule34easy-0.1.2.dist-info/METADATA
rule34easy-0.1.2.dist-info/RECORD
